vinyl_models/__init__.py
vinyl_models/prod_models.py
vinyl_models-0.5.0.dist-info/METADATA
vinyl_models-0.5.0.dist-info/WHEEL
vinyl_models-0.5.0.dist-info/licenses/LICENSE
vinyl_models-0.5.0.dist-info/RECORD
